Verilog/SumadorCompleto.v
module Mediosumador (
  input A,
  input B,
  output Suma,
  output Cout
);
  assign Suma = (A ^ B);
  assign Cout = (A & B);
endmodule

module SumadorCompleto (
  input Cin,
  input A,
  input B,
  output St,
  output Cout
);
  wire s0;
  wire s1;
  wire s2;
  Mediosumador Mediosumador_i0 (
    .A( A ),
    .B( B ),
    .Suma( s0 ),
    .Cout( s1 )
  );
  Mediosumador Mediosumador_i1 (
    .A( s0 ),
    .B( Cin ),
    .Suma( St ),
    .Cout( s2 )
  );
  assign Cout = (s2 | s1);
endmodule

SumadorCompleto_tb.v
//  A testbench for SumadorCompleto_tb
`timescale 1us/1ns

module SumadorCompleto_tb;
    reg Cin;
    reg A;
    reg B;
    wire St;
    wire Cout;

  SumadorCompleto SumadorCompleto0 (
    .Cin(Cin),
    .A(A),
    .B(B),
    .St(St),
    .Cout(Cout)
  );

    reg [4:0] patterns[0:7];
    integer i;

    initial begin
      patterns[0] = 5'b0_0_0_0_0;
      patterns[1] = 5'b0_0_1_1_0;
      patterns[2] = 5'b0_1_0_1_0;
      patterns[3] = 5'b0_1_1_0_1;
      patterns[4] = 5'b1_0_0_1_0;
      patterns[5] = 5'b1_0_1_0_1;
      patterns[6] = 5'b1_1_0_0_1;
      patterns[7] = 5'b1_1_1_1_1;

      for (i = 0; i < 8; i = i + 1)
      begin
        Cin = patterns[i][4];
        A = patterns[i][3];
        B = patterns[i][2];
        #10;
        if (patterns[i][1] !== 1'hx)
        begin
          if (St !== patterns[i][1])
          begin
            $display("%d:St: (assertion error). Expected %h, found %h", i, patterns[i][1], St);
            $finish;
          end
        end
        if (patterns[i][0] !== 1'hx)
        begin
          if (Cout !== patterns[i][0])
          begin
            $display("%d:Cout: (assertion error). Expected %h, found %h", i, patterns[i][0], Cout);
            $finish;
          end
        end
      end

      $display("All tests passed.");

    $dumpfile("SumadorCompletotop.vcd");
    $dumpvars(0, SumadorCompleto_tb);
  end
    endmodule

vcd/SumadorCompleto.vcd
$date
	Fri Oct  6 14:23:16 2023
$end
$version
	Icarus Verilog
$end
$timescale
	1ns
$end
$scope module SumadorCompleto_tb $end
$var wire 1 ! St $end
$var wire 1 " Cout $end
$var reg 1 # A $end
$var reg 1 $ B $end
$var reg 1 % Cin $end
$var integer 32 & i [31:0] $end
$scope module SumadorCompleto0 $end
$var wire 1 # A $end
$var wire 1 $ B $end
$var wire 1 % Cin $end
$var wire 1 " Cout $end
$var wire 1 ' s2 $end
$var wire 1 ( s1 $end
$var wire 1 ) s0 $end
$var wire 1 ! St $end
$scope module Mediosumador_i0 $end
$var wire 1 # A $end
$var wire 1 $ B $end
$var wire 1 ( Cout $end
$var wire 1 ) Suma $end
$upscope $end
$scope module Mediosumador_i1 $end
$var wire 1 ) A $end
$var wire 1 % B $end
$var wire 1 ' Cout $end
$var wire 1 ! Suma $end
$upscope $end
$upscope $end
$upscope $end
$enddefinitions $end
#0
$dumpvars
0)
0(
0'
b0 &
0%
0$
0#
0"
0!
$end
#10000
1!
1)
1$
b1 &
#20000
0$
1#
b10 &
#30000
0!
1"
0)
1(
1$
b11 &
#40000
0"
0(
1!
0$
0#
1%
b100 &
#50000
1"
0!
1'
1)
1$
b101 &
#60000
0$
1#
b110 &
#70000
1!
0'
0)
1(
1$
b111 &
#80000
b1000 &
